{
  "$schema": "https://developer.microsoft.com/json-schemas/fabric/item/report/definition/visualContainer/2.1.0/schema.json",
  "name": "e0678400c8d12645d4e7",
  "position": {
    "x": 266.75814751286453,
    "y": 463.25900514579763,
    "z": 11000,
    "height": 234.92281303602059,
    "width": 986.89536878216131,
    "tabOrder": 10000
  },
  "visual": {
    "visualType": "tableEx",
    "query": {
      "queryState": {
        "Values": {
          "projections": [
            {
              "field": {
                "Column": {
                  "Expression": {
                    "SourceRef": {
                      "Entity": "Dim_dataset"
                    }
                  },
                  "Property": "name"
                }
              },
              "queryRef": "Dim_dataset.name",
              "nativeQueryRef": "Modèles sémantiques",
              "displayName": "Modèles sémantiques"
            },
            {
              "field": {
                "Column": {
                  "Expression": {
                    "SourceRef": {
                      "Entity": "Dim_catalog_dataset"
                    }
                  },
                  "Property": "webURL"
                }
              },
              "queryRef": "Dim_catalog_dataset.webURL",
              "nativeQueryRef": "Doc",
              "displayName": "Doc"
            },
            {
              "field": {
                "Column": {
                  "Expression": {
                    "SourceRef": {
                      "Entity": "Dim_dataset"
                    }
                  },
                  "Property": "configuredBy"
                }
              },
              "queryRef": "Dim_dataset.configuredBy",
              "nativeQueryRef": "Propriétaire",
              "displayName": "Propriétaire"
            },
            {
              "field": {
                "Column": {
                  "Expression": {
                    "SourceRef": {
                      "Entity": "Fact_refresh_history"
                    }
                  },
                  "Property": "refreshType"
                }
              },
              "queryRef": "Fact_refresh_history.refreshType",
              "nativeQueryRef": "Refresh",
              "displayName": "Refresh"
            },
            {
              "field": {
                "Column": {
                  "Expression": {
                    "SourceRef": {
                      "Entity": "Fact_refresh_history"
                    }
                  },
                  "Property": "status"
                }
              },
              "queryRef": "Fact_refresh_history.status",
              "nativeQueryRef": "Statut",
              "displayName": "Statut"
            },
            {
              "field": {
                "Column": {
                  "Expression": {
                    "SourceRef": {
                      "Entity": "Fact_refresh_history"
                    }
                  },
                  "Property": "startTime"
                }
              },
              "queryRef": "Fact_refresh_history.startTime",
              "nativeQueryRef": "Début",
              "displayName": "Début"
            },
            {
              "field": {
                "Column": {
                  "Expression": {
                    "SourceRef": {
                      "Entity": "Fact_refresh_history"
                    }
                  },
                  "Property": "endTime"
                }
              },
              "queryRef": "Fact_refresh_history.endTime",
              "nativeQueryRef": "Fin",
              "displayName": "Fin"
            },
            {
              "field": {
                "Aggregation": {
                  "Expression": {
                    "Column": {
                      "Expression": {
                        "SourceRef": {
                          "Entity": "Fact_refresh_history"
                        }
                      },
                      "Property": "temps_actualisation"
                    }
                  },
                  "Function": 0
                }
              },
              "queryRef": "Sum(Fact_refresh_history.temps_actualisation)",
              "nativeQueryRef": "Durée",
              "displayName": "Durée"
            }
          ]
        }
      },
      "sortDefinition": {
        "sort": [
          {
            "field": {
              "Column": {
                "Expression": {
                  "SourceRef": {
                    "Entity": "Dim_dataset"
                  }
                },
                "Property": "name"
              }
            },
            "direction": "Descending"
          }
        ]
      }
    },
    "objects": {
      "grid": [
        {
          "properties": {
            "textSize": {
              "expr": {
                "Literal": {
                  "Value": "14D"
                }
              }
            },
            "rowPadding": {
              "expr": {
                "Literal": {
                  "Value": "5D"
                }
              }
            },
            "gridVertical": {
              "expr": {
                "Literal": {
                  "Value": "false"
                }
              }
            }
          }
        }
      ],
      "values": [
        {
          "properties": {
            "fontSize": {
              "expr": {
                "Literal": {
                  "Value": "8D"
                }
              }
            },
            "fontColorPrimary": {
              "solid": {
                "color": {
                  "expr": {
                    "Literal": {
                      "Value": "'#173B5B'"
                    }
                  }
                }
              }
            },
            "fontColorSecondary": {
              "solid": {
                "color": {
                  "expr": {
                    "Literal": {
                      "Value": "'#1C2D3E'"
                    }
                  }
                }
              }
            },
            "urlIcon": {
              "expr": {
                "Literal": {
                  "Value": "true"
                }
              }
            }
          }
        },
        {
          "properties": {},
          "selector": {
            "data": [
              {
                "dataViewWildcard": {
                  "matchingOption": 1
                }
              }
            ],
            "metadata": "Measures_Table.Total Sales"
          }
        },
        {
          "properties": {},
          "selector": {
            "data": [
              {
                "dataViewWildcard": {
                  "matchingOption": 1
                }
              }
            ],
            "metadata": "Measures_Table.Closed|Expec Date"
          }
        },
        {
          "properties": {},
          "selector": {
            "data": [
              {
                "dataViewWildcard": {
                  "matchingOption": 1
                }
              }
            ],
            "metadata": "Measures_Table.Closed|Expec Days"
          }
        },
        {
          "properties": {},
          "selector": {
            "data": [
              {
                "dataViewWildcard": {
                  "matchingOption": 1
                }
              }
            ],
            "metadata": "Measures_Table.Closed deals value %"
          }
        },
        {
          "properties": {},
          "selector": {
            "data": [
              {
                "dataViewWildcard": {
                  "matchingOption": 1
                }
              }
            ],
            "metadata": "Measures_Table.Closed deals value"
          }
        },
        {
          "properties": {},
          "selector": {
            "data": [
              {
                "dataViewWildcard": {
                  "matchingOption": 1
                }
              }
            ],
            "metadata": "Measures_Table.Status"
          }
        },
        {
          "properties": {
            "webURL": {
              "expr": {
                "Aggregation": {
                  "Expression": {
                    "Column": {
                      "Expression": {
                        "SourceRef": {
                          "Entity": "Dim_dataset"
                        }
                      },
                      "Property": "webUrl"
                    }
                  },
                  "Function": 3
                }
              }
            }
          },
          "selector": {
            "data": [
              {
                "dataViewWildcard": {
                  "matchingOption": 1
                }
              }
            ],
            "metadata": "Dim_dataset.name"
          }
        },
        {
          "properties": {},
          "selector": {
            "data": [
              {
                "dataViewWildcard": {
                  "matchingOption": 1
                }
              }
            ],
            "metadata": "Dim_dataset.configuredBy"
          }
        },
        {
          "properties": {
            "fontColor": {
              "solid": {
                "color": {
                  "expr": {
                    "Conditional": {
                      "Cases": [
                        {
                          "Condition": {
                            "Comparison": {
                              "ComparisonKind": 0,
                              "Left": {
                                "Aggregation": {
                                  "Expression": {
                                    "Column": {
                                      "Expression": {
                                        "SourceRef": {
                                          "Entity": "Fact_refresh_history"
                                        }
                                      },
                                      "Property": "status"
                                    }
                                  },
                                  "Function": 3
                                }
                              },
                              "Right": {
                                "Literal": {
                                  "Value": "'Failed'"
                                }
                              }
                            },
                            "Annotations": {
                              "PowerBI.SQExprEvaluationKind": 1,
                              "PowerBI.SQExprTextOperatorOption": 2
                            }
                          },
                          "Value": {
                            "Literal": {
                              "Value": "'#ec5d56'"
                            }
                          }
                        },
                        {
                          "Condition": {
                            "Comparison": {
                              "ComparisonKind": 0,
                              "Left": {
                                "Aggregation": {
                                  "Expression": {
                                    "Column": {
                                      "Expression": {
                                        "SourceRef": {
                                          "Entity": "Fact_refresh_history"
                                        }
                                      },
                                      "Property": "status"
                                    }
                                  },
                                  "Function": 3
                                }
                              },
                              "Right": {
                                "Literal": {
                                  "Value": "'Disabled'"
                                }
                              }
                            },
                            "Annotations": {
                              "PowerBI.SQExprEvaluationKind": 1,
                              "PowerBI.SQExprTextOperatorOption": 2
                            }
                          },
                          "Value": {
                            "Literal": {
                              "Value": "'#ffcd6d'"
                            }
                          }
                        },
                        {
                          "Condition": {
                            "Comparison": {
                              "ComparisonKind": 0,
                              "Left": {
                                "Aggregation": {
                                  "Expression": {
                                    "Column": {
                                      "Expression": {
                                        "SourceRef": {
                                          "Entity": "Fact_refresh_history"
                                        }
                                      },
                                      "Property": "status"
                                    }
                                  },
                                  "Function": 3
                                }
                              },
                              "Right": {
                                "Literal": {
                                  "Value": "'Completed'"
                                }
                              }
                            },
                            "Annotations": {
                              "PowerBI.SQExprEvaluationKind": 1,
                              "PowerBI.SQExprTextOperatorOption": 2
                            }
                          },
                          "Value": {
                            "Literal": {
                              "Value": "'#97c86d'"
                            }
                          }
                        }
                      ]
                    }
                  }
                }
              }
            }
          },
          "selector": {
            "data": [
              {
                "dataViewWildcard": {
                  "matchingOption": 1
                }
              }
            ],
            "metadata": "Fact_refresh_history.status"
          }
        },
        {
          "properties": {},
          "selector": {
            "data": [
              {
                "dataViewWildcard": {
                  "matchingOption": 1
                }
              }
            ],
            "metadata": "Fact_refresh_history.startTime"
          }
        },
        {
          "properties": {},
          "selector": {
            "data": [
              {
                "dataViewWildcard": {
                  "matchingOption": 1
                }
              }
            ],
            "metadata": "Fact_refresh_history.endTime"
          }
        },
        {
          "properties": {},
          "selector": {
            "data": [
              {
                "dataViewWildcard": {
                  "matchingOption": 1
                }
              }
            ],
            "metadata": "Fact_refresh_history.refreshType"
          }
        },
        {
          "properties": {
            "fontColor": {
              "solid": {
                "color": {
                  "expr": {
                    "Conditional": {
                      "Cases": [
                        {
                          "Condition": {
                            "Comparison": {
                              "ComparisonKind": 1,
                              "Left": {
                                "Aggregation": {
                                  "Expression": {
                                    "Column": {
                                      "Expression": {
                                        "SourceRef": {
                                          "Entity": "Fact_refresh_history"
                                        }
                                      },
                                      "Property": "temps_actualisation"
                                    }
                                  },
                                  "Function": 0
                                }
                              },
                              "Right": {
                                "Literal": {
                                  "Value": "30D"
                                }
                              }
                            }
                          },
                          "Value": {
                            "Literal": {
                              "Value": "'#ec5d56'"
                            }
                          }
                        },
                        {
                          "Condition": {
                            "And": {
                              "Left": {
                                "Comparison": {
                                  "ComparisonKind": 1,
                                  "Left": {
                                    "Aggregation": {
                                      "Expression": {
                                        "Column": {
                                          "Expression": {
                                            "SourceRef": {
                                              "Entity": "Fact_refresh_history"
                                            }
                                          },
                                          "Property": "temps_actualisation"
                                        }
                                      },
                                      "Function": 0
                                    }
                                  },
                                  "Right": {
                                    "Literal": {
                                      "Value": "10D"
                                    }
                                  }
                                }
                              },
                              "Right": {
                                "Comparison": {
                                  "ComparisonKind": 4,
                                  "Left": {
                                    "Aggregation": {
                                      "Expression": {
                                        "Column": {
                                          "Expression": {
                                            "SourceRef": {
                                              "Entity": "Fact_refresh_history"
                                            }
                                          },
                                          "Property": "temps_actualisation"
                                        }
                                      },
                                      "Function": 0
                                    }
                                  },
                                  "Right": {
                                    "Literal": {
                                      "Value": "30D"
                                    }
                                  }
                                }
                              }
                            }
                          },
                          "Value": {
                            "Literal": {
                              "Value": "'#ffcd6d'"
                            }
                          }
                        },
                        {
                          "Condition": {
                            "Comparison": {
                              "ComparisonKind": 4,
                              "Left": {
                                "Aggregation": {
                                  "Expression": {
                                    "Column": {
                                      "Expression": {
                                        "SourceRef": {
                                          "Entity": "Fact_refresh_history"
                                        }
                                      },
                                      "Property": "temps_actualisation"
                                    }
                                  },
                                  "Function": 0
                                }
                              },
                              "Right": {
                                "Literal": {
                                  "Value": "10D"
                                }
                              }
                            }
                          },
                          "Value": {
                            "Literal": {
                              "Value": "'#97c86d'"
                            }
                          }
                        }
                      ]
                    }
                  }
                }
              }
            }
          },
          "selector": {
            "data": [
              {
                "dataViewWildcard": {
                  "matchingOption": 1
                }
              }
            ],
            "metadata": "Sum(Fact_refresh_history.temps_actualisation)"
          }
        }
      ],
      "columnFormatting": [
        {
          "properties": {
            "dataBars": {
              "positiveColor": {
                "solid": {
                  "color": {
                    "expr": {
                      "Literal": {
                        "Value": "'#e6e6e6'"
                      }
                    }
                  }
                }
              },
              "negativeColor": {
                "solid": {
                  "color": {
                    "expr": {
                      "Literal": {
                        "Value": "'#efb5b9'"
                      }
                    }
                  }
                }
              },
              "axisColor": {
                "solid": {
                  "color": {
                    "expr": {
                      "Literal": {
                        "Value": "'#FFFFFF'"
                      }
                    }
                  }
                }
              },
              "reverseDirection": {
                "expr": {
                  "Literal": {
                    "Value": "false"
                  }
                }
              },
              "hideText": {
                "expr": {
                  "Literal": {
                    "Value": "false"
                  }
                }
              },
              "totalMatchingOption": {
                "expr": {
                  "Literal": {
                    "Value": "1L"
                  }
                }
              }
            },
            "labelDisplayUnits": {
              "expr": {
                "Literal": {
                  "Value": "1000D"
                }
              }
            },
            "labelPrecision": {
              "expr": {
                "Literal": {
                  "Value": "1L"
                }
              }
            }
          },
          "selector": {
            "metadata": "Measures_Table.Closed deals value"
          }
        },
        {
          "properties": {
            "labelDisplayUnits": {
              "expr": {
                "Literal": {
                  "Value": "1000D"
                }
              }
            }
          },
          "selector": {
            "metadata": "Measures_Table.Total Sales"
          }
        },
        {
          "properties": {
            "alignment": {
              "expr": {
                "Literal": {
                  "Value": "'Center'"
                }
              }
            }
          },
          "selector": {
            "metadata": "Measures_Table.Closed|Expec Date"
          }
        }
      ],
      "columnWidth": [
        {
          "properties": {
            "value": {
              "expr": {
                "Literal": {
                  "Value": "109D"
                }
              }
            }
          },
          "selector": {
            "metadata": "Measures_Table.Closed deals value"
          }
        },
        {
          "properties": {
            "value": {
              "expr": {
                "Literal": {
                  "Value": "237.22108496339933D"
                }
              }
            }
          },
          "selector": {
            "metadata": "Fact_CRM_Sales.Owner"
          }
        },
        {
          "properties": {
            "value": {
              "expr": {
                "Literal": {
                  "Value": "97D"
                }
              }
            }
          },
          "selector": {
            "metadata": "Measures_Table.Total Sales"
          }
        },
        {
          "properties": {
            "value": {
              "expr": {
                "Literal": {
                  "Value": "76D"
                }
              }
            }
          },
          "selector": {
            "metadata": "Measures_Table.Closed deals value %"
          }
        },
        {
          "properties": {
            "value": {
              "expr": {
                "Literal": {
                  "Value": "111D"
                }
              }
            }
          },
          "selector": {
            "metadata": "Fact_CRM_Sales.Agents"
          }
        },
        {
          "properties": {
            "value": {
              "expr": {
                "Literal": {
                  "Value": "162D"
                }
              }
            }
          },
          "selector": {
            "metadata": "Measures_Table.Closed|Expec Date"
          }
        },
        {
          "properties": {
            "value": {
              "expr": {
                "Literal": {
                  "Value": "51D"
                }
              }
            }
          },
          "selector": {
            "metadata": "Measures_Table.Closed|Expec Days"
          }
        },
        {
          "properties": {
            "value": {
              "expr": {
                "Literal": {
                  "Value": "155D"
                }
              }
            }
          },
          "selector": {
            "metadata": "Measures_Table.Status"
          }
        },
        {
          "properties": {
            "value": {
              "expr": {
                "Literal": {
                  "Value": "114D"
                }
              }
            }
          },
          "selector": {
            "metadata": "Measures_Table.Stage Measure"
          }
        },
        {
          "properties": {
            "value": {
              "expr": {
                "Literal": {
                  "Value": "97D"
                }
              }
            }
          },
          "selector": {
            "data": [
              {
                "scopeId": {
                  "Comparison": {
                    "ComparisonKind": 0,
                    "Left": {
                      "Column": {
                        "Expression": {
                          "SourceRef": {
                            "Entity": "Fact_CRM_Sales"
                          }
                        },
                        "Property": "Lead acquisition date"
                      }
                    },
                    "Right": {
                      "Literal": {
                        "Value": "datetime'2024-01-02T00:00:00'"
                      }
                    }
                  }
                }
              }
            ],
            "metadata": "Measures_Table.Total Sales"
          }
        },
        {
          "properties": {
            "value": {
              "expr": {
                "Literal": {
                  "Value": "109D"
                }
              }
            }
          },
          "selector": {
            "data": [
              {
                "scopeId": {
                  "Comparison": {
                    "ComparisonKind": 0,
                    "Left": {
                      "Column": {
                        "Expression": {
                          "SourceRef": {
                            "Entity": "Fact_CRM_Sales"
                          }
                        },
                        "Property": "Lead acquisition date"
                      }
                    },
                    "Right": {
                      "Literal": {
                        "Value": "datetime'2024-01-02T00:00:00'"
                      }
                    }
                  }
                }
              }
            ],
            "metadata": "Measures_Table.Closed deals value"
          }
        },
        {
          "properties": {
            "value": {
              "expr": {
                "Literal": {
                  "Value": "76D"
                }
              }
            }
          },
          "selector": {
            "data": [
              {
                "scopeId": {
                  "Comparison": {
                    "ComparisonKind": 0,
                    "Left": {
                      "Column": {
                        "Expression": {
                          "SourceRef": {
                            "Entity": "Fact_CRM_Sales"
                          }
                        },
                        "Property": "Lead acquisition date"
                      }
                    },
                    "Right": {
                      "Literal": {
                        "Value": "datetime'2024-01-02T00:00:00'"
                      }
                    }
                  }
                }
              }
            ],
            "metadata": "Measures_Table.Closed deals value %"
          }
        },
        {
          "properties": {
            "value": {
              "expr": {
                "Literal": {
                  "Value": "162D"
                }
              }
            }
          },
          "selector": {
            "data": [
              {
                "scopeId": {
                  "Comparison": {
                    "ComparisonKind": 0,
                    "Left": {
                      "Column": {
                        "Expression": {
                          "SourceRef": {
                            "Entity": "Fact_CRM_Sales"
                          }
                        },
                        "Property": "Lead acquisition date"
                      }
                    },
                    "Right": {
                      "Literal": {
                        "Value": "datetime'2024-01-02T00:00:00'"
                      }
                    }
                  }
                }
              }
            ],
            "metadata": "Measures_Table.Closed|Expec Date"
          }
        },
        {
          "properties": {
            "value": {
              "expr": {
                "Literal": {
                  "Value": "51D"
                }
              }
            }
          },
          "selector": {
            "data": [
              {
                "scopeId": {
                  "Comparison": {
                    "ComparisonKind": 0,
                    "Left": {
                      "Column": {
                        "Expression": {
                          "SourceRef": {
                            "Entity": "Fact_CRM_Sales"
                          }
                        },
                        "Property": "Lead acquisition date"
                      }
                    },
                    "Right": {
                      "Literal": {
                        "Value": "datetime'2024-01-02T00:00:00'"
                      }
                    }
                  }
                }
              }
            ],
            "metadata": "Measures_Table.Closed|Expec Days"
          }
        },
        {
          "properties": {
            "value": {
              "expr": {
                "Literal": {
                  "Value": "61D"
                }
              }
            }
          },
          "selector": {
            "data": [
              {
                "scopeId": {
                  "Comparison": {
                    "ComparisonKind": 0,
                    "Left": {
                      "Column": {
                        "Expression": {
                          "SourceRef": {
                            "Entity": "Fact_CRM_Sales"
                          }
                        },
                        "Property": "Lead acquisition date"
                      }
                    },
                    "Right": {
                      "Literal": {
                        "Value": "datetime'2024-01-02T00:00:00'"
                      }
                    }
                  }
                }
              }
            ],
            "metadata": "Measures_Table.Status"
          }
        },
        {
          "properties": {
            "value": {
              "expr": {
                "Literal": {
                  "Value": "57D"
                }
              }
            }
          },
          "selector": {
            "data": [
              {
                "scopeId": {
                  "Comparison": {
                    "ComparisonKind": 0,
                    "Left": {
                      "Column": {
                        "Expression": {
                          "SourceRef": {
                            "Entity": "Fact_CRM_Sales"
                          }
                        },
                        "Property": "Lead acquisition date"
                      }
                    },
                    "Right": {
                      "Literal": {
                        "Value": "datetime'2024-01-02T00:00:00'"
                      }
                    }
                  }
                }
              }
            ],
            "metadata": "Measures_Table.Stage Measure"
          }
        },
        {
          "properties": {
            "value": {
              "expr": {
                "Literal": {
                  "Value": "97D"
                }
              }
            }
          },
          "selector": {
            "data": [
              {
                "scopeId": {
                  "Comparison": {
                    "ComparisonKind": 0,
                    "Left": {
                      "Column": {
                        "Expression": {
                          "SourceRef": {
                            "Entity": "Fact_CRM_Sales"
                          }
                        },
                        "Property": "Lead acquisition date"
                      }
                    },
                    "Right": {
                      "Literal": {
                        "Value": "datetime'2024-01-03T00:00:00'"
                      }
                    }
                  }
                }
              }
            ],
            "metadata": "Measures_Table.Total Sales"
          }
        },
        {
          "properties": {
            "value": {
              "expr": {
                "Literal": {
                  "Value": "109D"
                }
              }
            }
          },
          "selector": {
            "data": [
              {
                "scopeId": {
                  "Comparison": {
                    "ComparisonKind": 0,
                    "Left": {
                      "Column": {
                        "Expression": {
                          "SourceRef": {
                            "Entity": "Fact_CRM_Sales"
                          }
                        },
                        "Property": "Lead acquisition date"
                      }
                    },
                    "Right": {
                      "Literal": {
                        "Value": "datetime'2024-01-03T00:00:00'"
                      }
                    }
                  }
                }
              }
            ],
            "metadata": "Measures_Table.Closed deals value"
          }
        },
        {
          "properties": {
            "value": {
              "expr": {
                "Literal": {
                  "Value": "76D"
                }
              }
            }
          },
          "selector": {
            "data": [
              {
                "scopeId": {
                  "Comparison": {
                    "ComparisonKind": 0,
                    "Left": {
                      "Column": {
                        "Expression": {
                          "SourceRef": {
                            "Entity": "Fact_CRM_Sales"
                          }
                        },
                        "Property": "Lead acquisition date"
                      }
                    },
                    "Right": {
                      "Literal": {
                        "Value": "datetime'2024-01-03T00:00:00'"
                      }
                    }
                  }
                }
              }
            ],
            "metadata": "Measures_Table.Closed deals value %"
          }
        },
        {
          "properties": {
            "value": {
              "expr": {
                "Literal": {
                  "Value": "162D"
                }
              }
            }
          },
          "selector": {
            "data": [
              {
                "scopeId": {
                  "Comparison": {
                    "ComparisonKind": 0,
                    "Left": {
                      "Column": {
                        "Expression": {
                          "SourceRef": {
                            "Entity": "Fact_CRM_Sales"
                          }
                        },
                        "Property": "Lead acquisition date"
                      }
                    },
                    "Right": {
                      "Literal": {
                        "Value": "datetime'2024-01-03T00:00:00'"
                      }
                    }
                  }
                }
              }
            ],
            "metadata": "Measures_Table.Closed|Expec Date"
          }
        },
        {
          "properties": {
            "value": {
              "expr": {
                "Literal": {
                  "Value": "51D"
                }
              }
            }
          },
          "selector": {
            "data": [
              {
                "scopeId": {
                  "Comparison": {
                    "ComparisonKind": 0,
                    "Left": {
                      "Column": {
                        "Expression": {
                          "SourceRef": {
                            "Entity": "Fact_CRM_Sales"
                          }
                        },
                        "Property": "Lead acquisition date"
                      }
                    },
                    "Right": {
                      "Literal": {
                        "Value": "datetime'2024-01-03T00:00:00'"
                      }
                    }
                  }
                }
              }
            ],
            "metadata": "Measures_Table.Closed|Expec Days"
          }
        },
        {
          "properties": {
            "value": {
              "expr": {
                "Literal": {
                  "Value": "61D"
                }
              }
            }
          },
          "selector": {
            "data": [
              {
                "scopeId": {
                  "Comparison": {
                    "ComparisonKind": 0,
                    "Left": {
                      "Column": {
                        "Expression": {
                          "SourceRef": {
                            "Entity": "Fact_CRM_Sales"
                          }
                        },
                        "Property": "Lead acquisition date"
                      }
                    },
                    "Right": {
                      "Literal": {
                        "Value": "datetime'2024-01-03T00:00:00'"
                      }
                    }
                  }
                }
              }
            ],
            "metadata": "Measures_Table.Status"
          }
        },
        {
          "properties": {
            "value": {
              "expr": {
                "Literal": {
                  "Value": "57D"
                }
              }
            }
          },
          "selector": {
            "data": [
              {
                "scopeId": {
                  "Comparison": {
                    "ComparisonKind": 0,
                    "Left": {
                      "Column": {
                        "Expression": {
                          "SourceRef": {
                            "Entity": "Fact_CRM_Sales"
                          }
                        },
                        "Property": "Lead acquisition date"
                      }
                    },
                    "Right": {
                      "Literal": {
                        "Value": "datetime'2024-01-03T00:00:00'"
                      }
                    }
                  }
                }
              }
            ],
            "metadata": "Measures_Table.Stage Measure"
          }
        },
        {
          "properties": {
            "value": {
              "expr": {
                "Literal": {
                  "Value": "97D"
                }
              }
            }
          },
          "selector": {
            "data": [
              {
                "scopeId": {
                  "Comparison": {
                    "ComparisonKind": 0,
                    "Left": {
                      "Column": {
                        "Expression": {
                          "SourceRef": {
                            "Entity": "Fact_CRM_Sales"
                          }
                        },
                        "Property": "Lead acquisition date"
                      }
                    },
                    "Right": {
                      "Literal": {
                        "Value": "datetime'2024-01-05T00:00:00'"
                      }
                    }
                  }
                }
              }
            ],
            "metadata": "Measures_Table.Total Sales"
          }
        },
        {
          "properties": {
            "value": {
              "expr": {
                "Literal": {
                  "Value": "109D"
                }
              }
            }
          },
          "selector": {
            "data": [
              {
                "scopeId": {
                  "Comparison": {
                    "ComparisonKind": 0,
                    "Left": {
                      "Column": {
                        "Expression": {
                          "SourceRef": {
                            "Entity": "Fact_CRM_Sales"
                          }
                        },
                        "Property": "Lead acquisition date"
                      }
                    },
                    "Right": {
                      "Literal": {
                        "Value": "datetime'2024-01-05T00:00:00'"
                      }
                    }
                  }
                }
              }
            ],
            "metadata": "Measures_Table.Closed deals value"
          }
        },
        {
          "properties": {
            "value": {
              "expr": {
                "Literal": {
                  "Value": "76D"
                }
              }
            }
          },
          "selector": {
            "data": [
              {
                "scopeId": {
                  "Comparison": {
                    "ComparisonKind": 0,
                    "Left": {
                      "Column": {
                        "Expression": {
                          "SourceRef": {
                            "Entity": "Fact_CRM_Sales"
                          }
                        },
                        "Property": "Lead acquisition date"
                      }
                    },
                    "Right": {
                      "Literal": {
                        "Value": "datetime'2024-01-05T00:00:00'"
                      }
                    }
                  }
                }
              }
            ],
            "metadata": "Measures_Table.Closed deals value %"
          }
        },
        {
          "properties": {
            "value": {
              "expr": {
                "Literal": {
                  "Value": "162D"
                }
              }
            }
          },
          "selector": {
            "data": [
              {
                "scopeId": {
                  "Comparison": {
                    "ComparisonKind": 0,
                    "Left": {
                      "Column": {
                        "Expression": {
                          "SourceRef": {
                            "Entity": "Fact_CRM_Sales"
                          }
                        },
                        "Property": "Lead acquisition date"
                      }
                    },
                    "Right": {
                      "Literal": {
                        "Value": "datetime'2024-01-05T00:00:00'"
                      }
                    }
                  }
                }
              }
            ],
            "metadata": "Measures_Table.Closed|Expec Date"
          }
        },
        {
          "properties": {
            "value": {
              "expr": {
                "Literal": {
                  "Value": "51D"
                }
              }
            }
          },
          "selector": {
            "data": [
              {
                "scopeId": {
                  "Comparison": {
                    "ComparisonKind": 0,
                    "Left": {
                      "Column": {
                        "Expression": {
                          "SourceRef": {
                            "Entity": "Fact_CRM_Sales"
                          }
                        },
                        "Property": "Lead acquisition date"
                      }
                    },
                    "Right": {
                      "Literal": {
                        "Value": "datetime'2024-01-05T00:00:00'"
                      }
                    }
                  }
                }
              }
            ],
            "metadata": "Measures_Table.Closed|Expec Days"
          }
        },
        {
          "properties": {
            "value": {
              "expr": {
                "Literal": {
                  "Value": "61D"
                }
              }
            }
          },
          "selector": {
            "data": [
              {
                "scopeId": {
                  "Comparison": {
                    "ComparisonKind": 0,
                    "Left": {
                      "Column": {
                        "Expression": {
                          "SourceRef": {
                            "Entity": "Fact_CRM_Sales"
                          }
                        },
                        "Property": "Lead acquisition date"
                      }
                    },
                    "Right": {
                      "Literal": {
                        "Value": "datetime'2024-01-05T00:00:00'"
                      }
                    }
                  }
                }
              }
            ],
            "metadata": "Measures_Table.Status"
          }
        },
        {
          "properties": {
            "value": {
              "expr": {
                "Literal": {
                  "Value": "57D"
                }
              }
            }
          },
          "selector": {
            "data": [
              {
                "scopeId": {
                  "Comparison": {
                    "ComparisonKind": 0,
                    "Left": {
                      "Column": {
                        "Expression": {
                          "SourceRef": {
                            "Entity": "Fact_CRM_Sales"
                          }
                        },
                        "Property": "Lead acquisition date"
                      }
                    },
                    "Right": {
                      "Literal": {
                        "Value": "datetime'2024-01-05T00:00:00'"
                      }
                    }
                  }
                }
              }
            ],
            "metadata": "Measures_Table.Stage Measure"
          }
        },
        {
          "properties": {
            "value": {
              "expr": {
                "Literal": {
                  "Value": "97D"
                }
              }
            }
          },
          "selector": {
            "data": [
              {
                "scopeId": {
                  "Comparison": {
                    "ComparisonKind": 0,
                    "Left": {
                      "Column": {
                        "Expression": {
                          "SourceRef": {
                            "Entity": "Fact_CRM_Sales"
                          }
                        },
                        "Property": "Lead acquisition date"
                      }
                    },
                    "Right": {
                      "Literal": {
                        "Value": "datetime'2024-01-06T00:00:00'"
                      }
                    }
                  }
                }
              }
            ],
            "metadata": "Measures_Table.Total Sales"
          }
        },
        {
          "properties": {
            "value": {
              "expr": {
                "Literal": {
                  "Value": "109D"
                }
              }
            }
          },
          "selector": {
            "data": [
              {
                "scopeId": {
                  "Comparison": {
                    "ComparisonKind": 0,
                    "Left": {
                      "Column": {
                        "Expression": {
                          "SourceRef": {
                            "Entity": "Fact_CRM_Sales"
                          }
                        },
                        "Property": "Lead acquisition date"
                      }
                    },
                    "Right": {
                      "Literal": {
                        "Value": "datetime'2024-01-06T00:00:00'"
                      }
                    }
                  }
                }
              }
            ],
            "metadata": "Measures_Table.Closed deals value"
          }
        },
        {
          "properties": {
            "value": {
              "expr": {
                "Literal": {
                  "Value": "76D"
                }
              }
            }
          },
          "selector": {
            "data": [
              {
                "scopeId": {
                  "Comparison": {
                    "ComparisonKind": 0,
                    "Left": {
                      "Column": {
                        "Expression": {
                          "SourceRef": {
                            "Entity": "Fact_CRM_Sales"
                          }
                        },
                        "Property": "Lead acquisition date"
                      }
                    },
                    "Right": {
                      "Literal": {
                        "Value": "datetime'2024-01-06T00:00:00'"
                      }
                    }
                  }
                }
              }
            ],
            "metadata": "Measures_Table.Closed deals value %"
          }
        },
        {
          "properties": {
            "value": {
              "expr": {
                "Literal": {
                  "Value": "162D"
                }
              }
            }
          },
          "selector": {
            "data": [
              {
                "scopeId": {
                  "Comparison": {
                    "ComparisonKind": 0,
                    "Left": {
                      "Column": {
                        "Expression": {
                          "SourceRef": {
                            "Entity": "Fact_CRM_Sales"
                          }
                        },
                        "Property": "Lead acquisition date"
                      }
                    },
                    "Right": {
                      "Literal": {
                        "Value": "datetime'2024-01-06T00:00:00'"
                      }
                    }
                  }
                }
              }
            ],
            "metadata": "Measures_Table.Closed|Expec Date"
          }
        },
        {
          "properties": {
            "value": {
              "expr": {
                "Literal": {
                  "Value": "51D"
                }
              }
            }
          },
          "selector": {
            "data": [
              {
                "scopeId": {
                  "Comparison": {
                    "ComparisonKind": 0,
                    "Left": {
                      "Column": {
                        "Expression": {
                          "SourceRef": {
                            "Entity": "Fact_CRM_Sales"
                          }
                        },
                        "Property": "Lead acquisition date"
                      }
                    },
                    "Right": {
                      "Literal": {
                        "Value": "datetime'2024-01-06T00:00:00'"
                      }
                    }
                  }
                }
              }
            ],
            "metadata": "Measures_Table.Closed|Expec Days"
          }
        },
        {
          "properties": {
            "value": {
              "expr": {
                "Literal": {
                  "Value": "126D"
                }
              }
            }
          },
          "selector": {
            "data": [
              {
                "scopeId": {
                  "Comparison": {
                    "ComparisonKind": 0,
                    "Left": {
                      "Column": {
                        "Expression": {
                          "SourceRef": {
                            "Entity": "Fact_CRM_Sales"
                          }
                        },
                        "Property": "Lead acquisition date"
                      }
                    },
                    "Right": {
                      "Literal": {
                        "Value": "datetime'2024-01-06T00:00:00'"
                      }
                    }
                  }
                }
              }
            ],
            "metadata": "Measures_Table.Status"
          }
        },
        {
          "properties": {
            "value": {
              "expr": {
                "Literal": {
                  "Value": "109D"
                }
              }
            }
          },
          "selector": {
            "data": [
              {
                "scopeId": {
                  "Comparison": {
                    "ComparisonKind": 0,
                    "Left": {
                      "Column": {
                        "Expression": {
                          "SourceRef": {
                            "Entity": "Fact_CRM_Sales"
                          }
                        },
                        "Property": "Lead acquisition date"
                      }
                    },
                    "Right": {
                      "Literal": {
                        "Value": "datetime'2024-01-06T00:00:00'"
                      }
                    }
                  }
                }
              }
            ],
            "metadata": "Measures_Table.Stage Measure"
          }
        },
        {
          "properties": {
            "value": {
              "expr": {
                "Literal": {
                  "Value": "97D"
                }
              }
            }
          },
          "selector": {
            "data": [
              {
                "scopeId": {
                  "Comparison": {
                    "ComparisonKind": 0,
                    "Left": {
                      "Column": {
                        "Expression": {
                          "SourceRef": {
                            "Entity": "Fact_CRM_Sales"
                          }
                        },
                        "Property": "Lead acquisition date"
                      }
                    },
                    "Right": {
                      "Literal": {
                        "Value": "datetime'2024-01-07T00:00:00'"
                      }
                    }
                  }
                }
              }
            ],
            "metadata": "Measures_Table.Total Sales"
          }
        },
        {
          "properties": {
            "value": {
              "expr": {
                "Literal": {
                  "Value": "109D"
                }
              }
            }
          },
          "selector": {
            "data": [
              {
                "scopeId": {
                  "Comparison": {
                    "ComparisonKind": 0,
                    "Left": {
                      "Column": {
                        "Expression": {
                          "SourceRef": {
                            "Entity": "Fact_CRM_Sales"
                          }
                        },
                        "Property": "Lead acquisition date"
                      }
                    },
                    "Right": {
                      "Literal": {
                        "Value": "datetime'2024-01-07T00:00:00'"
                      }
                    }
                  }
                }
              }
            ],
            "metadata": "Measures_Table.Closed deals value"
          }
        },
        {
          "properties": {
            "value": {
              "expr": {
                "Literal": {
                  "Value": "100D"
                }
              }
            }
          },
          "selector": {
            "metadata": "Min(Fact_CRM_Sales.Lead acquisition date)"
          }
        },
        {
          "properties": {
            "value": {
              "expr": {
                "Literal": {
                  "Value": "174.90014915268756D"
                }
              }
            }
          },
          "selector": {
            "metadata": "Dim_dataset.name"
          }
        },
        {
          "properties": {
            "value": {
              "expr": {
                "Literal": {
                  "Value": "219.24013611335153D"
                }
              }
            }
          },
          "selector": {
            "metadata": "Dim_dataset.configuredBy"
          }
        },
        {
          "properties": {
            "value": {
              "expr": {
                "Literal": {
                  "Value": "148.36337546707188D"
                }
              }
            }
          },
          "selector": {
            "metadata": "Fact_refresh_history.startTime"
          }
        },
        {
          "properties": {
            "value": {
              "expr": {
                "Literal": {
                  "Value": "138.65857881199688D"
                }
              }
            }
          },
          "selector": {
            "metadata": "Fact_refresh_history.endTime"
          }
        },
        {
          "properties": {
            "value": {
              "expr": {
                "Literal": {
                  "Value": "76D"
                }
              }
            }
          },
          "selector": {
            "metadata": "Fact_refresh_history.status"
          }
        },
        {
          "properties": {
            "value": {
              "expr": {
                "Literal": {
                  "Value": "82D"
                }
              }
            }
          },
          "selector": {
            "metadata": "Fact_refresh_history.refreshType"
          }
        },
        {
          "properties": {
            "value": {
              "expr": {
                "Literal": {
                  "Value": "65.97521329874336D"
                }
              }
            }
          },
          "selector": {
            "metadata": "Sum(Fact_refresh_history.temps_actualisation)"
          }
        },
        {
          "properties": {
            "value": {
              "expr": {
                "Literal": {
                  "Value": "35.42857667630163D"
                }
              }
            }
          },
          "selector": {
            "metadata": "Dim_catalog_dataset.webURL"
          }
        }
      ],
      "columnHeaders": [
        {
          "properties": {
            "autoSizeColumnWidth": {
              "expr": {
                "Literal": {
                  "Value": "false"
                }
              }
            },
            "fontSize": {
              "expr": {
                "Literal": {
                  "Value": "8D"
                }
              }
            },
            "bold": {
              "expr": {
                "Literal": {
                  "Value": "false"
                }
              }
            },
            "backColor": {
              "solid": {
                "color": {
                  "expr": {
                    "Literal": {
                      "Value": "'#F3F3F3'"
                    }
                  }
                }
              }
            },
            "fontColor": {
              "solid": {
                "color": {
                  "expr": {
                    "Literal": {
                      "Value": "'#1C2D3E'"
                    }
                  }
                }
              }
            }
          }
        }
      ],
      "general": [
        {
          "properties": {}
        }
      ],
      "total": [
        {
          "properties": {
            "totals": {
              "expr": {
                "Literal": {
                  "Value": "false"
                }
              }
            }
          }
        }
      ]
    },
    "visualContainerObjects": {
      "title": [
        {
          "properties": {
            "titleWrap": {
              "expr": {
                "Literal": {
                  "Value": "true"
                }
              }
            },
            "show": {
              "expr": {
                "Literal": {
                  "Value": "true"
                }
              }
            },
            "text": {
              "expr": {
                "Literal": {
                  "Value": "'Actualisation des modèles sémantiques'"
                }
              }
            },
            "fontSize": {
              "expr": {
                "Literal": {
                  "Value": "9D"
                }
              }
            },
            "fontColor": {
              "solid": {
                "color": {
                  "expr": {
                    "Literal": {
                      "Value": "'#1C2D3E'"
                    }
                  }
                }
              }
            },
            "fontFamily": {
              "expr": {
                "Literal": {
                  "Value": "'''Segoe UI'', wf_segoe-ui_normal, helvetica, arial, sans-serif'"
                }
              }
            },
            "bold": {
              "expr": {
                "Literal": {
                  "Value": "true"
                }
              }
            }
          }
        }
      ],
      "background": [
        {
          "properties": {
            "show": {
              "expr": {
                "Literal": {
                  "Value": "false"
                }
              }
            },
            "transparency": {
              "expr": {
                "Literal": {
                  "Value": "0D"
                }
              }
            }
          }
        }
      ],
      "border": [
        {
          "properties": {
            "width": {
              "expr": {
                "Literal": {
                  "Value": "1D"
                }
              }
            },
            "show": {
              "expr": {
                "Literal": {
                  "Value": "false"
                }
              }
            },
            "color": {
              "solid": {
                "color": {
                  "expr": {
                    "ThemeDataColor": {
                      "ColorId": 0,
                      "Percent": 0
                    }
                  }
                }
              }
            },
            "radius": {
              "expr": {
                "Literal": {
                  "Value": "10D"
                }
              }
            }
          }
        }
      ],
      "padding": [
        {
          "properties": {
            "top": {
              "expr": {
                "Literal": {
                  "Value": "10D"
                }
              }
            },
            "left": {
              "expr": {
                "Literal": {
                  "Value": "10D"
                }
              }
            },
            "bottom": {
              "expr": {
                "Literal": {
                  "Value": "10D"
                }
              }
            },
            "right": {
              "expr": {
                "Literal": {
                  "Value": "10D"
                }
              }
            }
          }
        }
      ],
      "subTitle": [
        {
          "properties": {
            "show": {
              "expr": {
                "Literal": {
                  "Value": "false"
                }
              }
            },
            "text": {
              "expr": {
                "Literal": {
                  "Value": "'Récupération en cours des détails des actualisations '"
                }
              }
            },
            "fontSize": {
              "expr": {
                "Literal": {
                  "Value": "8D"
                }
              }
            },
            "heading": {
              "expr": {
                "Literal": {
                  "Value": "'Normal'"
                }
              }
            }
          }
        }
      ],
      "spacing": [
        {
          "properties": {
            "verticalSpacing": {
              "expr": {
                "Literal": {
                  "Value": "10D"
                }
              }
            }
          }
        }
      ],
      "stylePreset": [
        {
          "properties": {
            "name": {
              "expr": {
                "Literal": {
                  "Value": "'None'"
                }
              }
            }
          }
        }
      ],
      "divider": [
        {
          "properties": {
            "show": {
              "expr": {
                "Literal": {
                  "Value": "false"
                }
              }
            }
          }
        }
      ]
    },
    "drillFilterOtherVisuals": true
  }
}